mcp_spec/__init__.py
mcp_spec/main.py
mcp_spec/prompts.py
mcp_spec-0.1.9.dist-info/METADATA
mcp_spec-0.1.9.dist-info/WHEEL
mcp_spec-0.1.9.dist-info/entry_points.txt
mcp_spec-0.1.9.dist-info/top_level.txt
mcp_spec-0.1.9.dist-info/RECORD
