Metadata-Version: 2.4
Name: mcp-spec
Version: 0.1.9
Summary: mcp for spec generation
Requires-Python: >=3.12
Requires-Dist: fastmcp>=2.10.6
